datagpu/__init__.py
datagpu/cache.py
datagpu/cleaner.py
datagpu/cli.py
datagpu/compiler.py
datagpu/deduper.py
datagpu/loader.py
datagpu/ranker.py
datagpu/types.py
datagpu/utils.py
datagpu-0.1.1.dist-info/licenses/LICENSE
datagpu-0.1.1.dist-info/METADATA
datagpu-0.1.1.dist-info/WHEEL
datagpu-0.1.1.dist-info/entry_points.txt
datagpu-0.1.1.dist-info/top_level.txt
datagpu-0.1.1.dist-info/RECORD
