Metadata-Version: 2.4
Name: datagpu
Version: 0.1.1
Summary: Open-source data compiler for AI training datasets
Author: Safariblocks Ltd.
Author-email: Celestino Kariuki <celestino@unlockwithjsr.com>
License: Apache-2.0
Project-URL: Homepage, https://github.com/Jasiri-App/datagpu
Project-URL: Repository, https://github.com/Jasiri-App/datagpu
Project-URL: Documentation, https://github.com/Jasiri-App/datagpu#readme
Keywords: machine-learning,data-processing,dataset,compiler,ai
Classifier: Development Status :: 3 - Alpha
Classifier: Intended Audience :: Developers
Classifier: Intended Audience :: Science/Research
Classifier: License :: OSI Approved :: Apache Software License
Classifier: Programming Language :: Python :: 3.11
Classifier: Programming Language :: Python :: 3.12
Classifier: Topic :: Scientific/Engineering :: Artificial Intelligence
Requires-Python: >=3.11
License-File: LICENSE
Requires-Dist: polars>=0.19.0
Requires-Dist: pyarrow>=14.0.0
Requires-Dist: xxhash>=3.4.0
Requires-Dist: scikit-learn>=1.3.0
Requires-Dist: numpy>=1.24.0
Requires-Dist: typer>=0.9.0
Requires-Dist: pyyaml>=6.0
Requires-Dist: rich>=13.0.0
Provides-Extra: dev
Requires-Dist: pytest>=7.4.0; extra == "dev"
Requires-Dist: pytest-cov>=4.1.0; extra == "dev"
Requires-Dist: black>=23.0.0; extra == "dev"
Requires-Dist: ruff>=0.1.0; extra == "dev"
Requires-Dist: mypy>=1.5.0; extra == "dev"
Provides-Extra: embeddings
Requires-Dist: sentence-transformers>=2.2.0; extra == "embeddings"
Requires-Dist: faiss-cpu>=1.7.4; extra == "embeddings"
Provides-Extra: distributed
Requires-Dist: ray>=2.7.0; extra == "distributed"
Dynamic: license-file
